{
  "transferencias": [
    {
      "id": "1",
      "valor": 35,
      "destino": "1212-1",
      "data": "2020-11-04T16:30:10.710Z"
    },
    {
      "id": "2",
      "valor": 40,
      "destino": "1213-1",
      "data": "2020-11-04T21:24:10.710Z"
    },
    {
      "id": "3",
      "valor": 12.5,
      "destino": "1214-1",
      "data": "2020-11-05T21:14:10.710Z"
    },
    {
      "valor": 313,
      "destino": "123",
      "data": "2022-04-12T18:32:36.189Z",
      "id": "8m2gxOD"
    },
    {
      "valor": 3000,
      "destino": "99898-01",
      "data": "2022-04-12T19:24:08.718Z",
      "id": "9CqoUb2"
    },
    {
      "valor": 220.5,
      "destino": "33111-10",
      "data": "2022-04-12T19:28:03.964Z",
      "id": "lycX1hX"
    }
  ]
}